BetheFluid/__init__.py
BetheFluid/calc.py
BetheFluid/observable.py
BetheFluid/plotter.py
BetheFluid/solver.py
BetheFluid/utils.py
BetheFluid/models/__init__.py
BetheFluid/models/calc_Lieb_Liniger.py
BetheFluid/models/calc_Q_Bosons.py
BetheFluid-0.6.dist-info/METADATA
BetheFluid-0.6.dist-info/WHEEL
BetheFluid-0.6.dist-info/top_level.txt
BetheFluid-0.6.dist-info/RECORD
