Metadata-Version: 2.1
Name: BetheFluid
Version: 0.6
Summary: Python package for solving GHD equations
Author: Antoni Lis, Milosz Panfil
Requires-Dist: numpy
Requires-Dist: matplotlib
Requires-Dist: scipy
Requires-Dist: tqdm
Requires-Dist: dill
